reflex_audio_capture/__init__.py
reflex_audio_capture/audio_capture.py
reflex_audio_capture-0.1.1.dist-info/METADATA
reflex_audio_capture-0.1.1.dist-info/WHEEL
reflex_audio_capture-0.1.1.dist-info/top_level.txt
reflex_audio_capture-0.1.1.dist-info/RECORD
