Metadata-Version: 2.4
Name: reflex-audio-capture
Version: 0.1.1
Summary: Experimental audio-recorder-polyfill component
Author-email: Masen Furer <m_github@0x26.net>
License: Apache-2.0
Project-URL: homepage, https://github.com/masenf/reflex-audio-capture
Keywords: reflex,reflex-custom-components
Classifier: Development Status :: 4 - Beta
Requires-Python: >=3.8
Requires-Dist: reflex>=0.6.6
Provides-Extra: dev
Requires-Dist: build; extra == "dev"
Requires-Dist: twine; extra == "dev"
